{"sync_token":"3mTIZ_wuEmaWfdhfZ7vzWjuWPXkl2mV4QamnI5Eq9UgifnjBLBjg6e-iHBD5gz7h8htQi1PPKtGwhL7ooWIndveEo-VWm59Ip7gjhl8B6392Rpw","temp_id_mapping":{},"full_sync":true,"projects":[{"is_favorite":0,"color":48,"collapsed":0,"inbox_project":true,"child_order":0,"id":1489536361,"name":"Inbox","is_deleted":0,"parent_id":null,"legacy_id":147359081,"shared":false,"is_archived":0},{"name":"BLYS","is_favorite":0,"color":48,"is_deleted":0,"collapsed":0,"parent_id":null,"child_order":1,"is_archived":0,"shared":false,"id":2214856308},{"name":"desk organization 30_ x 35.5_","is_favorite":0,"color":48,"is_deleted":0,"collapsed":0,"parent_id":null,"child_order":2,"is_archived":0,"shared":false,"id":2211772159},{"name":"shopping list","is_favorite":0,"color":48,"is_deleted":0,"collapsed":1,"parent_id":null,"child_order":3,"is_archived":0,"shared":false,"id":2166795770},{"name":"Costco","is_favorite":0,"color":48,"is_deleted":0,"collapsed":0,"parent_id":2166795770,"child_order":1,"is_archived":0,"shared":false,"id":2203890778},{"name":"test","is_favorite":0,"color":48,"is_deleted":0,"collapsed":0,"parent_id":null,"child_order":4,"is_archived":0,"shared":false,"id":2211042545},{"name":"mobility","is_favorite":0,"color":48,"is_deleted":0,"collapsed":0,"parent_id":null,"child_order":5,"is_archived":0,"shared":false,"id":2207928533},{"name":"mobility - sidebar","is_favorite":0,"color":48,"is_deleted":0,"collapsed":0,"parent_id":null,"child_order":6,"is_archived":0,"shared":false,"id":2214667293},{"name":"GoDaddy","is_favorite":0,"color":48,"is_deleted":0,"collapsed":1,"parent_id":null,"child_order":7,"is_archived":0,"shared":false,"id":2207530749},{"name":"refund component","is_favorite":0,"color":48,"is_deleted":0,"collapsed":0,"parent_id":2207530749,"child_order":1,"is_archived":0,"shared":false,"id":2207530760},{"name":"career","is_favorite":0,"color":48,"is_deleted":0,"collapsed":0,"parent_id":null,"child_order":8,"is_archived":0,"shared":false,"id":2208192297},{"name":"errands","is_favorite":0,"color":48,"is_deleted":0,"collapsed":0,"parent_id":null,"child_order":9,"is_archived":0,"shared":false,"id":2207884141},{"name":"chores","is_favorite":0,"color":48,"is_deleted":0,"collapsed":0,"parent_id":null,"child_order":10,"is_archived":0,"shared":false,"id":2207808442},{"name":"soft skills","is_favorite":0,"color":48,"is_deleted":0,"collapsed":0,"parent_id":null,"child_order":11,"is_archived":0,"shared":false,"id":2205873199},{"name":"...to","is_favorite":0,"color":48,"is_deleted":0,"collapsed":1,"parent_id":null,"child_order":12,"is_archived":0,"shared":false,"id":2205573063},{"name":"to listen","is_favorite":0,"color":48,"is_deleted":0,"collapsed":0,"parent_id":2205573063,"child_order":1,"is_archived":0,"shared":false,"id":2205573020},{"name":"food to try","is_favorite":0,"color":48,"is_deleted":0,"collapsed":1,"parent_id":2205573063,"child_order":2,"is_archived":0,"shared":false,"id":2201379233},{"name":"tried","is_favorite":0,"color":48,"is_deleted":0,"collapsed":0,"parent_id":2201379233,"child_order":1,"is_archived":0,"shared":false,"id":2205572953},{"name":"to watch","is_favorite":0,"color":48,"is_deleted":0,"collapsed":0,"parent_id":2205573063,"child_order":3,"is_archived":0,"shared":false,"id":2202052908},{"name":"places to visit","is_favorite":0,"color":48,"is_deleted":0,"collapsed":1,"parent_id":2205573063,"child_order":4,"is_archived":0,"shared":false,"id":2202090461},{"name":"visited","is_favorite":0,"color":48,"is_deleted":0,"collapsed":0,"parent_id":2202090461,"child_order":1,"is_archived":0,"shared":false,"id":2205572977},{"name":"to d/l for DJ","is_favorite":0,"color":48,"is_deleted":0,"collapsed":0,"parent_id":2205573063,"child_order":5,"is_archived":0,"shared":false,"id":2197249119},{"name":"video games to try","is_favorite":0,"color":48,"is_deleted":0,"collapsed":1,"parent_id":2205573063,"child_order":6,"is_archived":0,"shared":false,"id":2197864129},{"name":"to read","is_favorite":0,"color":48,"is_deleted":0,"collapsed":0,"parent_id":2205573063,"child_order":7,"is_archived":0,"shared":false,"id":2207968197},{"name":"travel plans","is_favorite":0,"color":48,"is_deleted":0,"collapsed":0,"parent_id":null,"child_order":13,"is_archived":0,"shared":false,"id":2202271080},{"name":"GBm","is_favorite":0,"color":48,"is_deleted":0,"collapsed":0,"parent_id":null,"child_order":14,"is_archived":0,"shared":false,"id":2201891996},{"name":"misc","is_favorite":0,"color":48,"is_deleted":0,"collapsed":0,"parent_id":null,"child_order":15,"is_archived":0,"shared":false,"id":2203503368},{"name":"climate change","is_favorite":0,"color":48,"is_deleted":0,"collapsed":0,"parent_id":null,"child_order":16,"is_archived":0,"shared":false,"id":2207765451},{"name":"product reviews","is_favorite":0,"color":48,"is_deleted":0,"collapsed":0,"parent_id":null,"child_order":17,"is_archived":0,"shared":false,"id":2207884127},{"name":"Samsung S9_","is_favorite":0,"color":48,"is_deleted":0,"collapsed":0,"parent_id":2207884127,"child_order":1,"is_archived":0,"shared":false,"id":2204582367},{"name":"Google Play Music complaints","is_favorite":0,"color":48,"is_deleted":0,"collapsed":0,"parent_id":2207884127,"child_order":2,"is_archived":0,"shared":false,"id":2207529026},{"name":"zzz","is_favorite":0,"color":48,"is_deleted":0,"collapsed":0,"parent_id":null,"child_order":18,"is_archived":0,"shared":false,"id":2208005657},{"name":"Salt Fat Acid Heat","is_favorite":0,"color":48,"is_deleted":0,"collapsed":0,"parent_id":null,"child_order":19,"is_archived":0,"shared":false,"id":2208840269},{"name":"nak","is_favorite":0,"color":48,"is_deleted":0,"collapsed":0,"parent_id":null,"child_order":20,"is_archived":0,"shared":false,"id":2211581557},{"name":"clothes","is_favorite":0,"color":48,"is_deleted":0,"collapsed":0,"parent_id":2211581557,"child_order":1,"is_archived":0,"shared":false,"id":2212926966},{"name":"overnight","is_favorite":0,"color":48,"is_deleted":0,"collapsed":0,"parent_id":2211581557,"child_order":2,"is_archived":0,"shared":false,"id":2212926529},{"name":"exercise","is_favorite":0,"color":48,"is_deleted":0,"collapsed":0,"parent_id":2211581557,"child_order":3,"is_archived":0,"shared":false,"id":2212926515}]}